pvi/Anslscan.py
pvi/Inascan.py
pvi/Snmpscan.py
pvi/__about__.py
pvi/__init__.py
pvi/pvi_objects/Connection.py
pvi/pvi_objects/Cpu.py
pvi/pvi_objects/Device.py
pvi/pvi_objects/Error.py
pvi/pvi_objects/Helpers.py
pvi/pvi_objects/Line.py
pvi/pvi_objects/Module.py
pvi/pvi_objects/Object.py
pvi/pvi_objects/Station.py
pvi/pvi_objects/Task.py
pvi/pvi_objects/Variable.py
pvi/pvi_objects/VariableTypeDescription.py
pvi/pvi_objects/__init__.py
pvi/pvi_objects/include/__init__.py
pvi/pvi_objects/include/common_h.py
pvi/pvi_objects/include/pvi_h.py
pvi/utils/BrDataObjectFile.py
pvi/utils/BrFile.py
pvi/utils/BrLoggerFile.py
pvi/utils/BrProfilerDataFile.py
pvi/utils/__init__.py
pvipy-1.2.7.dist-info/METADATA
pvipy-1.2.7.dist-info/WHEEL
pvipy-1.2.7.dist-info/entry_points.txt
pvipy-1.2.7.dist-info/licenses/LICENSE
pvipy-1.2.7.dist-info/RECORD
