Metadata-Version: 2.4
Name: pvipy
Version: 1.2.7
Summary: Python connector for B&R Pvi (process visualization interface)
Project-URL: Homepage, https://hilch.github.io/Pvi.py/
Project-URL: Bug Tracker, https://github.com/hilch/Pvi.py/issues
Author: Christoph Hilchenbach
License-File: LICENSE
Classifier: License :: OSI Approved :: MIT License
Classifier: Operating System :: Microsoft :: Windows
Classifier: Programming Language :: Python :: 3
Requires-Python: >=3.8
